jiveapi/__init__.py
jiveapi/api.py
jiveapi/content.py
jiveapi/exceptions.py
jiveapi/jiveresponse.py
jiveapi/utils.py
jiveapi/version.py
jiveapi/sphinx_theme/__init__.py
jiveapi/sphinx_theme/builder.py
jiveapi/sphinx_theme/layout.html
jiveapi/sphinx_theme/theme.conf
jiveapi/tests/__init__.py
jiveapi/tests/conftest.py
jiveapi/tests/test_api.py
jiveapi/tests/test_content.py
jiveapi/tests/test_exceptions.py
jiveapi/tests/test_helpers.py
jiveapi/tests/test_jiveresponse.py
jiveapi/tests/test_utils.py
jiveapi/tests/test_version.py
jiveapi/tests/fixtures/__init__.py
jiveapi/tests/fixtures/cassettes/__init__.py
jiveapi/tests/fixtures/html/__init__.py
jiveapi-1.0.0.dist-info/DESCRIPTION.rst
jiveapi-1.0.0.dist-info/METADATA
jiveapi-1.0.0.dist-info/RECORD
jiveapi-1.0.0.dist-info/WHEEL
jiveapi-1.0.0.dist-info/entry_points.txt
jiveapi-1.0.0.dist-info/metadata.json
jiveapi-1.0.0.dist-info/top_level.txt
