Metadata-Version: 2.0
Name: jiveapi
Version: 1.0.0
Summary: Simple and limited Python client for Jive collaboration software ReST API v3.
Home-page: https://github.com/jantman/jiveapi
Author: Jason Antman
Author-email: jason@jasonantman.com
License: UNKNOWN
Keywords: jive collaboration client
Platform: UNKNOWN
Classifier: Development Status :: 7 - Inactive
Classifier: License :: OSI Approved :: GNU Affero General Public License v3 or later (AGPLv3+)
Classifier: Natural Language :: English
Classifier: Operating System :: OS Independent
Classifier: Programming Language :: Python
Classifier: Programming Language :: Python :: 3
Classifier: Programming Language :: Python :: 3.4
Classifier: Programming Language :: Python :: 3.5
Classifier: Programming Language :: Python :: 3.6
Classifier: Programming Language :: Python :: 3.7
Classifier: Topic :: Documentation
Classifier: Topic :: Office/Business
Requires-Dist: requests (<3.0.0)
Requires-Dist: premailer (<4.0.0,>=3.0.0)
Requires-Dist: lxml (<5.0.0,>=4.0.0)
